kanban/__init__.py
kanban/cli.py
kanban/config.py
kanban/merge.py
kanban/models.py
kanban/search.py
kanban/search_old.py
kanban/storage.py
kanban/validators.py
juno_kanban-1.17.0.dist-info/METADATA
juno_kanban-1.17.0.dist-info/WHEEL
juno_kanban-1.17.0.dist-info/entry_points.txt
juno_kanban-1.17.0.dist-info/top_level.txt
juno_kanban-1.17.0.dist-info/RECORD
