Metadata-Version: 2.4
Name: juno-kanban
Version: 1.17.0
Summary: A shell-based kanban task manager with NDJSON storage and high-performance search
Home-page: https://github.com/askbudi/feedback-shell
Author: Juno AI
Author-email: support@juno.ai
Project-URL: Bug Reports, https://github.com/askbudi/feedback-shell/issues
Project-URL: Source, https://github.com/askbudi/feedback-shell
Project-URL: Documentation, https://github.com/askbudi/feedback-shell#readme
Keywords: kanban task-manager cli ndjson productivity
Classifier: Development Status :: 4 - Beta
Classifier: Intended Audience :: Developers
Classifier: License :: OSI Approved :: MIT License
Classifier: Operating System :: OS Independent
Classifier: Programming Language :: Python :: 3
Classifier: Programming Language :: Python :: 3.8
Classifier: Programming Language :: Python :: 3.9
Classifier: Programming Language :: Python :: 3.10
Classifier: Programming Language :: Python :: 3.11
Classifier: Programming Language :: Python :: 3.12
Classifier: Topic :: Software Development :: Bug Tracking
Classifier: Topic :: Software Development :: Libraries :: Python Modules
Classifier: Topic :: Utilities
Requires-Python: >=3.8
Dynamic: author
Dynamic: author-email
Dynamic: classifier
Dynamic: description
Dynamic: description-content-type
Dynamic: home-page
Dynamic: keywords
Dynamic: project-url
Dynamic: requires-python
Dynamic: summary
